LICENSE.txt
MANIFEST.in
README.rst
setup.cfg
setup.py
version.txt
docs/AUTHORS.txt
docs/HISTORY.rst
docs/INSTALL.rst
docs/LICENSE.GPL
vnccollab/__init__.py
vnccollab.redmine.egg-info/PKG-INFO
vnccollab.redmine.egg-info/SOURCES.txt
vnccollab.redmine.egg-info/dependency_links.txt
vnccollab.redmine.egg-info/entry_points.txt
vnccollab.redmine.egg-info/namespace_packages.txt
vnccollab.redmine.egg-info/not-zip-safe
vnccollab.redmine.egg-info/requires.txt
vnccollab.redmine.egg-info/top_level.txt
vnccollab/redmine/__init__.py
vnccollab/redmine/config.py
vnccollab/redmine/configure.zcml
vnccollab/redmine/content.py
vnccollab/redmine/interfaces.py
vnccollab/redmine/overrides.zcml
vnccollab/redmine/testing.py
vnccollab/redmine/userdataschema.py
vnccollab/redmine/util.py
vnccollab/redmine/browser/__init__.py
vnccollab/redmine/browser/configure.zcml
vnccollab/redmine/browser/viewlets.py
vnccollab/redmine/browser/templates/related_redmine_tickets.pt
vnccollab/redmine/portlets/__init__.py
vnccollab/redmine/portlets/configure.zcml
vnccollab/redmine/portlets/redmine_tickets.py
vnccollab/redmine/portlets/templates/redmine_tickets.pt
vnccollab/redmine/profiles/default/browserlayer.xml
vnccollab/redmine/profiles/default/memberdata_properties.xml
vnccollab/redmine/profiles/default/metadata.xml
vnccollab/redmine/profiles/default/portlets.xml
vnccollab/redmine/profiles/default/registry.xml
vnccollab/redmine/profiles/default/viewlets.xml
vnccollab/redmine/tests/__init__.py
vnccollab/redmine/tests/_mock.py
vnccollab/redmine/tests/base.py
vnccollab/redmine/tests/test_install.py
vnccollab/redmine/tests/test_portlets.py
vnccollab/redmine/tests/test_util.py
vnccollab/redmine/tests/test_viewlets.py
vnccollab/redmine/upgrades/__init__.py
vnccollab/redmine/upgrades/configure.zcml
vnccollab/redmine/upgrades/replaceportlets.py
vnccollab/redmine/upgrades/upgrades.py