Metadata-Version: 1.1
Name: vnccollab.redmine
Version: 1.0.7
Summary: VNC Collaboration Redmine AddOn.
Home-page: https://github.com/vnc-biz/vnccollab.redmine
Author: Jose Dinuncio
Author-email: jose.dinuncio@vnc.biz
License: gpl
Keywords: redmine
Platform: UNKNOWN
Classifier: Environment :: Web Environment
Classifier: Framework :: Plone
Classifier: Programming Language :: Python
Classifier: Operating System :: OS Independent
